FIFO.v
module FIFO
	#(
		parameter DATO_WIDTH = 3,
		parameter FIFO_LENGTH = 5
	)(
		input wclk,
		input [DATO_WIDTH-1:0] datin,
		input rclk,
		input rst,
		output reg [DATO_WIDTH-1:0] datout,
		output reg full,
		output reg empy,
		output reg dato
	);

// Registers	
	reg [DATO_WIDTH-1:0] f [0:(FIFO_LENGTH-1)];
	
	reg orwr;
	
	reg [2:0] cont = 0;
	reg [2:0] contw = 0;
	reg [2:0] contr = 0;
	
	always @(posedge orwr) begin

		if(rst) begin
			f[0] = 3'b000;
			f[1] = 3'b000;
			f[2] = 3'b000;
			f[3] = 3'b000;
			f[4] = 3'b000;
			cont <= 0;
			contw <= 0;
			contr <= 0;
			datout <= 0;
		end else begin
			case({rclk,wclk})
				2'b01:
					if(~full) begin
						f[contw] <= datin;
						contw <= contw + 3'b001;	
						if(contw >= (FIFO_LENGTH - 1)) contw <= 3'b000;
						cont <= cont + 3'b001;
					end

				2'b10:
					if(~empy) begin
						datout <= f[contr];
						f[contr] <= 0;
						contr <= contr + 3'b001;
						if(contr >= (FIFO_LENGTH - 1)) contr <= 3'b000;
						cont <= cont - 3'b001;
					end

				2'b11:
					if(full) begin

						datout <= f[contr];
						f[contr] <= 0;
						contr <= contr + 3'b001;
						if(contr >= (FIFO_LENGTH - 1)) contr <= 3'b000;

						f[contw] <= datin;
						contw <= contw + 3'b001;	
						if(contw >= (FIFO_LENGTH - 1)) contw <= 3'b000;

					end else if(empy) begin
						
						datout <= datin;

					end else begin

						if(~full) begin
							f[contw] <= datin;
							contw <= contw + 3'b001;	
							if(contw >= (FIFO_LENGTH - 1)) contw <= 3'b000;
						end

						if(~empy) begin
							datout <= f[contr];
							f[contr] <= 0;
							contr <= contr + 3'b001;
							if(contr >= (FIFO_LENGTH - 1)) contr <= 3'b000;
						end
					end
			endcase
		end

	end
	
	always @(*) begin
		orwr = wclk | rclk | rst;
		if(cont == 0) begin
			empy = 1;
			dato = 0;
			full = 0;
		end
		if(cont > 0) begin
			empy = 0;
			dato = 1;
			full = 0;
		end
		if(cont == FIFO_LENGTH) begin
			empy = 0;
			dato = 0;
			full = 1;
		end
	end

endmodule

FIFO_TB.v
`timescale 1ns / 1ns

module FIFO_TB;
	reg wclk = 0;
	reg wr;
	reg [2:0] datin;
	
	reg rclk = 0;
	reg rd;
	wire [2:0] datout;
	
	wire full;
	wire empy;
	wire dato;
	
	reg rst = 0;
	
	FIFO uut(.wclk(wclk), .datin(datin), .rclk(rclk), .datout(datout), .full(full), .empy(empy), .dato(dato), .rst(rst));

	initial begin
		
		datin = 2;
		wclk = 1;
		#2;
		wclk = 0;
		#2;
		
		datin = 6;
		wclk = 1;
		#2;
		wclk = 0;
		#2;
		
		datin = 4;
		wclk = 1;
		#2;
		wclk = 0;
		#2;
		
		datin = 1;
		wclk = 1;
		#2;
		wclk = 0;
		#2;
		
		datin = 7;
		wclk = 1;
		#2;
		wclk = 0;
		#2;
		
		datin = 4;
		wclk = 1;
		#2;
		wclk = 0;
		#2;

		datin = 4;
		wclk = 1;
		rclk = 1;
		#2;
		wclk = 0;
		rclk = 0;
		#2;
		
		rclk = 1;
		#2;
		rclk = 0;
		#2;
		
		rclk = 1;
		#2;
		rclk = 0;
		#2;
		
		rclk = 1;
		#2;
		rclk = 0;
		#2;

		rst = 1;
		#2;
		rst = 0;
		#2;
		
		datin = 1;
		wclk = 1;
		#2
		wclk = 0;
		#2
		
		datin = 5;
		wclk = 1;
		#2
		wclk = 0;
		#2
		
		datin = 6;
		wclk = 1;
		#2
		wclk = 0;
		#2
		
		rclk = 1;
		#2;
		rclk = 0;
		#2;
		
		rclk = 1;
		#2;
		rclk = 0;
		#2;
		
		rclk = 1;
		#2;
		rclk = 0;
		#2;
		
		rclk = 1;
		#2;
		rclk = 0;
		#2;
		
		rclk = 1;
		#2;
		rclk = 0;
		#2;
		
		datin = 4;
		rclk = 1;
		wclk = 1;
		#2;
		rclk = 0;
		wclk = 0;
		#2;
		
		
	end

	initial begin: TEST_CASE
		$dumpfile("FIFO_TB.vcd");
		$dumpvars(-1,uut);
		#(20000) $finish;
	end

endmodule

simulation/FIFO_TB.vcd
$date
	Thu Mar 15 13:38:35 2018
$end
$version
	Icarus Verilog
$end
$timescale
	1ns
$end
$scope module FIFO_TB $end
$scope module uut $end
$var wire 3 ! datin [2:0] $end
$var wire 1 " rclk $end
$var wire 1 # rst $end
$var wire 1 $ wclk $end
$var reg 3 % cont [2:0] $end
$var reg 3 & contr [2:0] $end
$var reg 3 ' contw [2:0] $end
$var reg 1 ( dato $end
$var reg 3 ) datout [2:0] $end
$var reg 1 * empy $end
$var reg 1 + full $end
$var reg 1 , orwr $end
$upscope $end
$upscope $end
$enddefinitions $end
#0
$dumpvars
1,
0+
0*
bx )
1(
b1 '
b0 &
b1 %
1$
0#
0"
b10 !
$end
#2
0,
0$
#4
b10 %
b10 '
1,
1$
b110 !
#6
0,
0$
#8
b11 %
b11 '
1,
1$
b100 !
#10
0,
0$
#12
b100 %
b100 '
1,
1$
b1 !
#14
0,
0$
#16
1+
0(
b101 %
b0 '
1,
1$
b111 !
#18
1+
0(
0,
0$
#20
1+
0(
1,
1$
b100 !
#22
1+
0(
0,
0$
#24
b1 '
b1 &
b10 )
1+
0(
1,
1"
1$
#26
1+
0(
0,
0"
0$
#28
b100 %
b10 &
b110 )
0+
1(
1,
1"
#30
0,
0"
#32
b11 %
b11 &
b100 )
1,
1"
#34
0,
0"
#36
b10 %
b100 &
b1 )
1,
1"
#38
0,
0"
#40
0(
1*
b0 &
b0 '
b0 %
1,
1#
#42
0,
0#
#44
1(
0*
b1 %
b1 '
1,
1$
b1 !
#46
0,
0$
#48
b10 %
b10 '
1,
1$
b101 !
#50
0,
0$
#52
b11 %
b11 '
1,
1$
b110 !
#54
0,
0$
#56
b10 %
b1 &
1,
1"
#58
0,
0"
#60
b1 %
b10 &
b101 )
1,
1"
#62
0,
0"
#64
0(
1*
b0 %
b11 &
b110 )
1,
1"
#66
0,
0"
#68
1,
1"
#70
0,
0"
#72
1,
1"
#74
0,
0"
#76
b100 )
1,
1$
1"
b100 !
#78
0,
0$
0"
