FIFO.v
module FIFO(wclk,wr,datin,rclk,rd,datout,full,empy,dato,rst);

	input wclk;
	input wr;
	input [2:0] datin;
	
	input rclk;
	input rd;
	output reg [2:0] datout;
	
	output reg full;
	output reg empy;
	output reg dato;
	
	input rst;
	
	reg [2:0] f [0:4];
	/*
	reg [2:0] f1;
	reg [2:0] f2;
	reg [2:0] f3;
	reg [2:0] f4;
	*/
	
	reg orwr;
	
	reg [2:0] cont = 0;
	reg d = 0;
		
	reg [2:0] contw = 0;
	reg [2:0] contr = 0;
	
	always @(posedge wclk) begin
	
		if(wr == 1 && cont <= 4) begin
			f[contw] = datin;
			
			if(contw == 4) contw = 3'b000;
			else contw = contw + 3'b001;
			
		end
	
	end
	
	always @(posedge rclk) begin
		
		if(rd == 1 && cont > 0) begin
			datout = f[contr];
			f[contr] = 0;
			
			if(contr == 4) contr = 3'b000;
			else contr = contr + 3'b001;
			
		end
		
	end
	
	always @(posedge orwr) begin
		
		if(rd == 1 && cont >= 0) cont = cont - 3'b001;
		if(wr == 1 && cont <= 4) cont = cont + 3'b001;
		
	end
	
	always @(*) begin
	
		orwr = wclk | rclk;
		/*
		if(rst == 1) begin
			f[0] = 3'b000;
			f[1] = 3'b000;
			f[2] = 3'b000;
			f[3] = 3'b000;
			f[4] = 3'b000;
		end
	*/
		if(cont == 0) begin
			empy = 1;
			dato = 0;
			full = 0;
		end
	
		if(cont > 0) begin
			empy = 0;
			dato = 1;
			full = 0;
		end
	
		if(cont == 5) begin
			empy = 0;
			dato = 0;
			full = 1;
		end
		
	end

endmodule

FIFO_TB.v
`timescale 1ns / 1ns

module FIFO_TB;
	reg wclk = 0;
	reg wr;
	reg [2:0] datin;
	
	reg rclk = 0;
	reg rd;
	wire [2:0] datout;
	
	wire full;
	wire empy;
	wire dato;
	
	reg rst;
	
	FIFO uut(.wclk(wclk), .wr(wr), .datin(datin), .rclk(rclk), .rd(rd), .datout(datout), .full(full), .empy(empy), .dato(dato), .rst(rst));

	initial begin
		
		wr = 1;
		datin = 2;
		wclk = 1;
		#2;
		wclk = 0;
		#2;
		
		datin = 6;
		wclk = 1;
		#2;
		wclk = 0;
		#2;
		
		datin = 4;
		wclk = 1;
		#2;
		wclk = 0;
		#2;
		
		datin = 1;
		wclk = 1;
		#2;
		wclk = 0;
		#2;
		
		datin = 7;
		wclk = 1;
		#2;
		wclk = 0;
		#2;
		
		datin = 4;
		wclk = 1;
		#2;
		wclk = 0;
		wr = 0;
		
		rd = 1;
		rclk = 1;
		#2;
		rclk = 0;
		#2;
		
		rclk = 1;
		#2;
		rclk = 0;
		#2;
		
		rclk = 1;
		#2;
		rclk = 0;
		#2;
		rd = 0;
		
		wr = 1;
		datin = 1;
		wclk = 1;
		#2
		wclk = 0;
		#2
		
		datin = 5;
		wclk = 1;
		#2
		wclk = 0;
		#2
		
		datin = 6;
		wclk = 1;
		#2
		wclk = 0;
		wr = 0;
		#2
		
		rd = 1;
		rclk = 1;
		#2;
		rclk = 0;
		#2;
		
		rclk = 1;
		#2;
		rclk = 0;
		#2;
		
		rclk = 1;
		#2;
		rclk = 0;
		#2;
		
		rclk = 1;
		#2;
		rclk = 0;
		#2;
		
		rclk = 1;
		#2;
		rclk = 0;
		#2;
		rd = 0;
		
		
	end

	initial begin: TEST_CASE
		$dumpfile("FIFO_TB.vcd");
		$dumpvars(-1,uut);
		#(20000) $finish;
	end

endmodule

simulation/FIFO_TB.vcd
$date
	Tue Mar  6 12:25:33 2018
$end
$version
	Icarus Verilog
$end
$timescale
	1ns
$end
$scope module FIFO_TB $end
$scope module uut $end
$var wire 3 ! datin [2:0] $end
$var wire 1 " rclk $end
$var wire 1 # rd $end
$var wire 1 $ rst $end
$var wire 1 % wclk $end
$var wire 1 & wr $end
$var reg 3 ' cont [2:0] $end
$var reg 3 ( contr [2:0] $end
$var reg 3 ) contw [2:0] $end
$var reg 1 * d $end
$var reg 1 + dato $end
$var reg 3 , datout [2:0] $end
$var reg 1 - empy $end
$var reg 1 . full $end
$var reg 1 / orwr $end
$upscope $end
$upscope $end
$enddefinitions $end
#0
$dumpvars
1/
0.
0-
bx ,
1+
0*
b1 )
b0 (
b1 '
1&
1%
x$
x#
0"
b10 !
$end
#2
0/
0%
#4
b10 '
1/
b10 )
1%
b110 !
#6
0/
0%
#8
b11 '
1/
b11 )
1%
b100 !
#10
0/
0%
#12
b100 '
1/
b100 )
1%
b1 !
#14
0/
0%
#16
1.
0+
b101 '
1/
b0 )
1%
b111 !
#18
1.
0+
0/
0%
#20
1.
0+
1/
1%
b100 !
#22
b1 (
b10 ,
1.
0+
1"
1#
0&
0%
#24
1.
0+
0/
0"
#26
b100 '
0.
1+
1/
b10 (
b110 ,
1"
#28
0/
0"
#30
b11 '
1/
b11 (
b100 ,
1"
#32
0/
0"
#34
b100 '
1/
b1 )
1%
b1 !
1&
0#
#36
0/
0%
#38
1.
0+
b101 '
1/
b10 )
1%
b101 !
#40
1.
0+
0/
0%
#42
1.
0+
1/
1%
b110 !
#44
1.
0+
0/
0&
0%
#46
b100 '
0.
1+
1/
b100 (
b1 ,
1"
1#
#48
0/
0"
#50
b11 '
1/
b0 (
b111 ,
1"
#52
0/
0"
#54
b10 '
1/
b1 (
b1 ,
1"
#56
0/
0"
#58
b1 '
1/
b10 (
b101 ,
1"
#60
0/
0"
#62
0+
1-
b0 '
1/
b11 (
b0 ,
1"
#64
0/
0"
#66
0#
